captcha9kw/__init__.py
captcha9kw/captcha9kw.py
captcha9kw-0.2.1.dist-info/LICENSE
captcha9kw-0.2.1.dist-info/WHEEL
captcha9kw-0.2.1.dist-info/METADATA
captcha9kw-0.2.1.dist-info/RECORD
