Metadata-Version: 2.1
Name: captcha9kw
Version: 0.2.1
Summary: A simple package for interacting with the 9kw.eu anti-captcha service.
Home-page: https://github.com/WereCatf/captcha9kw/
License: MIT
Author: WereCatf
Author-email: werecatf@outlook.com
Maintainer: WereCatf
Maintainer-email: werecatf@outlook.com
Requires-Python: >=3.7,<4.0
Classifier: Intended Audience :: Developers
Classifier: License :: OSI Approved :: MIT License
Classifier: Programming Language :: Python :: 3
Classifier: Programming Language :: Python :: 3.10
Classifier: Programming Language :: Python :: 3.7
Classifier: Programming Language :: Python :: 3.8
Classifier: Programming Language :: Python :: 3.9
Classifier: Topic :: Software Development :: Libraries :: Python Modules
Requires-Dist: filetype (>=1.0.8,<2.0.0)
Requires-Dist: importlib-metadata (>=1.0,<2.0); python_version < "3.8"
Requires-Dist: requests (>=2.26.0,<3.0.0)
Requires-Dist: validators (>=0.18.2,<0.19.0)
Project-URL: Documentation, https://captcha9kw.readthedocs.io/
Project-URL: Repository, https://github.com/WereCatf/captcha9kw/
